codec_cub/__init__.py
codec_cub/__main__.py
codec_cub/common.py
codec_cub/config.py
codec_cub/py.typed
codec_cub/_internal/__init__.py
codec_cub/_internal/_info.py
codec_cub/_internal/_version.py
codec_cub/_internal/_version.pyi
codec_cub/_internal/_versioning.py
codec_cub/_internal/cli.py
codec_cub/_internal/debug.py
codec_cub/general/README.md
codec_cub/general/__init__.py
codec_cub/general/base_file_handler.py
codec_cub/general/file_info.py
codec_cub/general/file_lock.py
codec_cub/general/helpers.py
codec_cub/general/mock_text.py
codec_cub/general/textio_utility.py
codec_cub/jsonl/__init__.py
codec_cub/jsonl/file_handler.py
codec_cub/jsonl/utils.py
codec_cub/jsons/__init__.py
codec_cub/jsons/file_handler.py
codec_cub/message_pack/README.md
codec_cub/message_pack/__init__.py
codec_cub/message_pack/_packing.py
codec_cub/message_pack/_unpacking.py
codec_cub/message_pack/file_handler.py
codec_cub/message_pack/msg_pack_handler.py
codec_cub/message_pack/packing.py
codec_cub/message_pack/unpacking.py
codec_cub/message_pack/common/__init__.py
codec_cub/message_pack/common/_fix_families.py
codec_cub/message_pack/common/_msgpack_tag.py
codec_cub/message_pack/common/exceptions.py
codec_cub/nix/README.md
codec_cub/nix/__init__.py
codec_cub/nix/codec.py
codec_cub/nix/encoder.py
codec_cub/nix/file_handler.py
codec_cub/nix/parser.py
codec_cub/nix/utils.py
codec_cub/pythons/README.md
codec_cub/pythons/__init__.py
codec_cub/pythons/_buffer.py
codec_cub/pythons/_protocols.py
codec_cub/pythons/code_section.py
codec_cub/pythons/codec.py
codec_cub/pythons/common.py
codec_cub/pythons/file_builder.py
codec_cub/pythons/helpers.py
codec_cub/pythons/parts.py
codec_cub/pythons/python_data_writer.py
codec_cub/pythons/python_db_helper.py
codec_cub/pythons/spec.md
codec_cub/pythons/type_annotation.py
codec_cub/pythons/builders/__init__.py
codec_cub/pythons/builders/class_builder.py
codec_cub/pythons/builders/docstring_builder.py
codec_cub/pythons/builders/enum_builder.py
codec_cub-0.0.16.dist-info/METADATA
codec_cub-0.0.16.dist-info/WHEEL
codec_cub-0.0.16.dist-info/entry_points.txt
codec_cub-0.0.16.dist-info/RECORD
