Metadata-Version: 2.4
Name: codec-cub
Version: 0.0.16
Summary: Parsing and encoding various codec configuration formats.
Author-email: chaz <bright.lid5647@fastmail.com>
Requires-Python: >=3.12
Requires-Dist: frozen-cub>=0.1.8
Requires-Dist: funcy-bear>=0.0.24
Requires-Dist: lark>=1.3.1
Requires-Dist: lazy-bear>=0.0.11
Requires-Dist: pyyaml>=6.0.3
Requires-Dist: singleton-base>=1.0.5
Requires-Dist: tomli-w>=1.2.0
Requires-Dist: tomlkit>=0.13.3
